cryptonator.py
cryptonator-0.0.4.dist-info/LICENSE
cryptonator-0.0.4.dist-info/METADATA
cryptonator-0.0.4.dist-info/WHEEL
cryptonator-0.0.4.dist-info/top_level.txt
cryptonator-0.0.4.dist-info/RECORD
