Metadata-Version: 2.1
Name: cryptonator
Version: 0.0.4
Summary: A simple wrapper for the cryptonator exchange rate API.
Home-page: https://github.com/aldur/cryptonator
Author: Adriano Di Luzio
Author-email: adrianodl@hotmail.it
License: MIT
Keywords: cryptonator
Platform: UNKNOWN
Classifier: Programming Language :: Python
Classifier: Programming Language :: Python :: 2
Classifier: Programming Language :: Python :: 2.7
Classifier: Programming Language :: Python :: 3
Classifier: Programming Language :: Python :: 3.4
Classifier: Programming Language :: Python :: 3.5
Classifier: Programming Language :: Python :: 3.6
Classifier: Programming Language :: Python :: 3.7
Classifier: Programming Language :: Python :: 3.8
Classifier: Development Status :: 6 - Mature
Classifier: Intended Audience :: Developers
Classifier: Intended Audience :: Financial and Insurance Industry
Classifier: Intended Audience :: Information Technology
Classifier: License :: OSI Approved :: MIT License
Classifier: Operating System :: OS Independent
Classifier: Topic :: Office/Business :: Financial
Requires-Dist: requests
